{"meta":{"name":"4K HOLLYWOOD","id":"just2471","type":"channel","posterShape":"landscape","videos":[{"id":"just247stream_1_0","title":"47 Meters Down: Uncaged (2019) 4K"},{"id":"just247stream_1_1","title":"Inglourious Basterds (2009) 4K"},{"id":"just247stream_1_2","title":"Uncut Gems (2019) 4K"},{"id":"just247stream_1_3","title":"22 July (2018) 4K"},{"id":"just247stream_1_4","title":"7500 (2019) 4K"},{"id":"just247stream_1_5","title":"Brittany Runs a Marathon (2019) 4K"},{"id":"just247stream_1_6","title":"Da 5 Bloods (2020) 4K"},{"id":"just247stream_1_7","title":"Desperados (2020) 4K"},{"id":"just247stream_1_8","title":"Equal Standard (2020) 4K"},{"id":"just247stream_1_9","title":"Eurovision Song Contest: The Story of Fire Saga (2020) 4K"},{"id":"just247stream_1_10","title":"Holiday Rush (2019) 4K"},{"id":"just247stream_1_11","title":"Into the Darkness (2020) 4K"},{"id":"just247stream_1_12","title":"Lady and the Tramp (2019) 4K"},{"id":"just247stream_1_13","title":"32 Malasana Street (2020) 4K"},{"id":"just247stream_1_14","title":"Once Upon a Time… in Hollywood (2019) 4K"},{"id":"just247stream_1_15","title":"Radioactive (2020) 4K"},{"id":"just247stream_1_16","title":"Spaceballs (1987) 4K"},{"id":"just247stream_1_17","title":"The Aeronauts (2019) 4K"},{"id":"just247stream_1_18","title":"The Black Cauldron (1985) 4K"},{"id":"just247stream_1_19","title":"The Old Guard (2020) 4K"},{"id":"just247stream_1_20","title":"The Swing of Things (2020) 4K"},{"id":"just247stream_1_21","title":"Timmy Failure: Mistakes Were Made (2020) 4K"},{"id":"just247stream_1_22","title":"Togo (2019) 4K"},{"id":"just247stream_1_23","title":"Volition (2019) 4K"},{"id":"just247stream_1_24","title":"Who Framed Roger Rabbit (1988) 4K"},{"id":"just247stream_1_25","title":"Coma (2019) 4K"},{"id":"just247stream_1_26","title":"The Hunger Games (2012) 4K"},{"id":"just247stream_1_27","title":"The Hunger Games: Catching Fire (2013) 4K"},{"id":"just247stream_1_28","title":"The Hunger Games: Mockingjay - Part 1 (2014) 4K"},{"id":"just247stream_1_29","title":"Downhill (2020) 4K"},{"id":"just247stream_1_30","title":"SamSam (2020) 4K"},{"id":"just247stream_1_31","title":"Think Like a Dog (2020) 4K"},{"id":"just247stream_1_32","title":"2012 (2009) 4K"},{"id":"just247stream_1_33","title":"Anna (2019) 4K"},{"id":"just247stream_1_34","title":"6 Underground (2019) 4K"},{"id":"just247stream_1_35","title":"A Bug's Life (1998) 4K"},{"id":"just247stream_1_36","title":"Bohemian Rhapsody (2018) 4K"},{"id":"just247stream_1_37","title":"Guardians of the Galaxy (2014) 4K"},{"id":"just247stream_1_38","title":" Inc. (2001) 4K"},{"id":"just247stream_1_39","title":" Inc. (2001) 4K"},{"id":"just247stream_1_40","title":"Monsters University (2013) 4K"},{"id":"just247stream_1_41","title":"Monsters University (2013) 4K"},{"id":"just247stream_1_42","title":"Stargirl (2020) 4K"},{"id":"just247stream_1_43","title":"Stargirl (2020) 4K"},{"id":"just247stream_1_44","title":"The Aeronauts (2019) 4K"},{"id":"just247stream_1_45","title":"Togo (2019) 4K"},{"id":"just247stream_1_46","title":"Up (2009) 4K"},{"id":"just247stream_1_47","title":"Who Framed Roger Rabbit (1988) 4K"},{"id":"just247stream_1_48","title":"21 Jump Street (2012) 4K"},{"id":"just247stream_1_49","title":"Jason Bourne (2016) 4K"},{"id":"just247stream_1_50","title":"Sherlock Holmes: A Game of Shadows (2011) 4K"},{"id":"just247stream_1_51","title":"A Hidden Life (2019) 4K"},{"id":"just247stream_1_52","title":"Batman: Death in the Family (2020) 4K"},{"id":"just247stream_1_53","title":"Downfalls High (2021) 4K"},{"id":"just247stream_1_54","title":"The Book of Life (2014) 4K"},{"id":"just247stream_1_55","title":"Police (2020) 4K"},{"id":"just247stream_1_56","title":"Palmer (2021) 4K"},{"id":"just247stream_1_57","title":"News of the World (2020) 4K"},{"id":"just247stream_1_58","title":"The Little Things (2021) 4K"},{"id":"just247stream_1_59","title":"The Croods: A New Age (2020) 4K"},{"id":"just247stream_1_60","title":"One Night in Miami... (2020) 4K"}]}}