{"meta":{"name":"FITE TV PASS","id":"just24724","type":"channel","posterShape":"landscape","videos":[{"id":"just247stream_24_0","title":"Fite TV 247"},{"id":"just247stream_24_1","title":"Fite TV 1"},{"id":"just247stream_24_2","title":"Fite TV 2"},{"id":"just247stream_24_3","title":"Fite TV 3"},{"id":"just247stream_24_4","title":"Fite TV 4"},{"id":"just247stream_24_5","title":"Fite TV 5"},{"id":"just247stream_24_6","title":"Fite TV 6"},{"id":"just247stream_24_7","title":"Fite TV 7"},{"id":"just247stream_24_8","title":"Fite TV 8"},{"id":"just247stream_24_9","title":"Fite TV 9"},{"id":"just247stream_24_10","title":"Fite TV 10"},{"id":"just247stream_24_11","title":"Fite TV 11"},{"id":"just247stream_24_12","title":"Fite TV 12"},{"id":"just247stream_24_13","title":"Fite TV 13"},{"id":"just247stream_24_14","title":"Fite TV 14"},{"id":"just247stream_24_15","title":"Fite TV 15"}]}}